rfc1924/__init__.py
rfc1924/rfc1924.py
rfc1924/test_rfc1924.py
rfc1924-0.3.2.dist-info/LICENSE
rfc1924-0.3.2.dist-info/METADATA
rfc1924-0.3.2.dist-info/WHEEL
rfc1924-0.3.2.dist-info/top_level.txt
rfc1924-0.3.2.dist-info/RECORD
