Metadata-Version: 2.1
Name: rfc1924
Version: 0.3.2
Summary: Implementation of RFC 1924
Home-page: https://github.com/0xflotus/rfc1924
Author: 0xflotus
Author-email: 0xflotus+pypi@gmail.com
License: MIT
Classifier: License :: OSI Approved :: MIT License
Classifier: Programming Language :: Python :: 3
Classifier: Programming Language :: Python :: 3.9
License-File: LICENSE
